sg/__init__.py
sg/__main__.py
sg/sg.py
sg/version.py
sg.py-1.2.1.dist-info/LICENSE
sg.py-1.2.1.dist-info/METADATA
sg.py-1.2.1.dist-info/WHEEL
sg.py-1.2.1.dist-info/entry_points.txt
sg.py-1.2.1.dist-info/top_level.txt
sg.py-1.2.1.dist-info/RECORD
