Metadata-Version: 2.1
Name: sg.py
Version: 1.2.1
Summary: Simple static site generator.
Home-page: https://github.com/venthur/sg
Author: Bastian Venthur
Author-email: mail@venthur.de
License: MIT
Keywords: markdown site generator cli
Platform: UNKNOWN
Classifier: Development Status :: 5 - Production/Stable
Classifier: Intended Audience :: Developers
Classifier: License :: OSI Approved :: MIT License
Classifier: Programming Language :: Python :: 3
Requires-Python: >=3
Requires-Dist: markdown
Provides-Extra: dev
Requires-Dist: flake8 ; extra == 'dev'
Requires-Dist: pytest ; extra == 'dev'
Requires-Dist: pytest-cov ; extra == 'dev'
